dcodex/__init__.py
dcodex/admin.py
dcodex/apps.py
dcodex/distance.py
dcodex/forms.py
dcodex/management/commands/_dcodex_commands.py
dcodex/management/commands/accordance.py
dcodex/management/commands/connectdecks.py
dcodex/management/commands/fixalllocations.py
dcodex/management/commands/fixlocations.py
dcodex/management/commands/fixs71.py
dcodex/management/commands/import_pdfs.py
dcodex/management/commands/latex.py
dcodex/management/commands/tei.py
dcodex/migrations/0001_initial.py
dcodex/migrations/0002_userprofile.py
dcodex/migrations/0003_auto_20190920_1333.py
dcodex/migrations/0004_auto_20190927_0054.py
dcodex/migrations/0005_auto_20200526_1559.py
dcodex/migrations/0006_remove_group_members.py
dcodex/migrations/0007_delete_membership.py
dcodex/migrations/0008_auto_20200526_2053.py
dcodex/migrations/0009_group.py
dcodex/migrations/0010_groupmembershipbase.py
dcodex/migrations/0011_groupmembershipall_groupmembershiprange.py
dcodex/migrations/0012_auto_20200526_2205.py
dcodex/migrations/0013_auto_20200527_2210.py
dcodex/migrations/0014_delete_groupmembershiprange.py
dcodex/migrations/0015_delete_groupmembershipall.py
dcodex/migrations/0016_delete_groupmembershipbase.py
dcodex/migrations/0017_delete_group.py
dcodex/migrations/0018_delete_groupbase.py
dcodex/migrations/0019_auto_20200527_2213.py
dcodex/migrations/0020_affiliationbase_name.py
dcodex/migrations/0021_affiliationverses.py
dcodex/migrations/0022_auto_20200803_1646.py
dcodex/migrations/0023_affiliationexcludeverses.py
dcodex/migrations/0024_auto_20200809_1431.py
dcodex/migrations/0025_auto_20200809_1536.py
dcodex/migrations/0026_auto_20201004_1045.py
dcodex/migrations/0027_manuscript_markup.py
dcodex/migrations/0028_auto_20201004_1050.py
dcodex/migrations/0029_manuscript_text_direction.py
dcodex/migrations/0030_auto_20201122_2300.py
dcodex/migrations/0031_auto_20201124_0944.py
dcodex/migrations/0032_auto_20201126_2325.py
dcodex/migrations/0033_simplearabicmarkup.py
dcodex-1.0.3.dist-info/LICENSE
dcodex-1.0.3.dist-info/WHEEL
dcodex-1.0.3.dist-info/METADATA
dcodex-1.0.3.dist-info/RECORD
