Metadata-Version: 2.1
Name: dcodex
Version: 1.0.3
Summary: A software framework for manuscript analysis
Home-page: https://github.com/rbturnbull/dcodex
License: Apache-2.0
Author: Robert Turnbull
Author-email: robert.turnbull@unimelb.edu.au
Requires-Python: >=3.8,<3.10
Classifier: License :: OSI Approved :: Apache Software License
Classifier: Programming Language :: Python :: 3
Classifier: Programming Language :: Python :: 3.8
Classifier: Programming Language :: Python :: 3.9
Requires-Dist: Django (>=3.2.6,<4.0.0)
Requires-Dist: beautifulsoup4 (>=4.9.3,<5.0.0)
Requires-Dist: django-admin-sortable2 (>=1.0,<2.0)
Requires-Dist: django-filer (>=2.0.2,<3.0.0)
Requires-Dist: django-guardian (>=2.4.0,<3.0.0)
Requires-Dist: django-imagedeck (>=0.3.3,<0.4.0)
Requires-Dist: django-polymorphic (>=3.0.0,<4.0.0)
Requires-Dist: gotoh (>=0.1.1,<0.2.0)
Requires-Dist: lxml (>=4.6.3,<5.0.0)
Requires-Dist: matplotlib (>=3.4.2,<4.0.0)
Requires-Dist: numpy (>=1.21.1,<2.0.0)
Requires-Dist: pandas (>=1.3.1,<2.0.0)
Requires-Dist: python-Levenshtein (>=0.12.2,<0.13.0)
Requires-Dist: pyxDamerauLevenshtein (>=1.7.0,<2.0.0)
Requires-Dist: regex (>=2021.8.3,<2022.0.0)
Requires-Dist: scipy (>=1.7.1,<2.0.0)
Project-URL: Repository, https://github.com/rbturnbull/dcodex
